orangebox/__init__.py
orangebox/context.py
orangebox/decoders.py
orangebox/events.py
orangebox/parser.py
orangebox/predictors.py
orangebox/reader.py
orangebox/tools.py
orangebox/types.py
orangebox-0.3.1.data/scripts/bb2csv
orangebox-0.3.1.data/scripts/bb2gpx
orangebox-0.3.1.data/scripts/bbsplit
orangebox-0.3.1.dist-info/LICENSE
orangebox-0.3.1.dist-info/METADATA
orangebox-0.3.1.dist-info/WHEEL
orangebox-0.3.1.dist-info/top_level.txt
orangebox-0.3.1.dist-info/RECORD
